README.md
setup.cfg
setup.py
floatingparser/__init__.py
floatingparser/floating_mail_sender.py
floatingparser/floating_parser.py
floatingparser/floating_statistics.py
floatingparser/floating_visualizer.py
floatingparser/floating_web.py
floatingparser/main.py
floatingparser.egg-info/PKG-INFO
floatingparser.egg-info/SOURCES.txt
floatingparser.egg-info/dependency_links.txt
floatingparser.egg-info/not-zip-safe
floatingparser.egg-info/top_level.txt