Metadata-Version: 2.1
Name: floatingparser
Version: 1.0.1
Summary: Parser for floating server logs
Author-email: vladislaus.shabalin@yandex.ru
